pyresx/ResXWriter.py
pyresx/__init__.py
pyresx/pyresx.py
pyresx-1.0.0.dist-info/LICENSE
pyresx-1.0.0.dist-info/METADATA
pyresx-1.0.0.dist-info/WHEEL
pyresx-1.0.0.dist-info/top_level.txt
pyresx-1.0.0.dist-info/RECORD
