Metadata-Version: 2.1
Name: pyresx
Version: 1.0.0
Summary: .resx file writer for python
Home-page: https://github.com/cola314/pyresx
Author: cola314
Author-email: ubj020314@gmail.com
License: UNKNOWN
Platform: UNKNOWN
Classifier: Programming Language :: Python :: 3
Classifier: License :: OSI Approved :: MIT License
Classifier: Operating System :: OS Independent
Requires-Python: >=3.6
